github_oss_contributions/__init__.py
github_oss_contributions/cli.py
github_oss_contributions/main.py
github_oss_contributions-0.3.1.dist-info/LICENSE
github_oss_contributions-0.3.1.dist-info/METADATA
github_oss_contributions-0.3.1.dist-info/WHEEL
github_oss_contributions-0.3.1.dist-info/entry_points.txt
github_oss_contributions-0.3.1.dist-info/top_level.txt
github_oss_contributions-0.3.1.dist-info/RECORD
