Metadata-Version: 2.1
Name: github-oss-contributions
Version: 0.3.1
Summary: Fetch organizations where a user created issues or PRs for Open Source
Author: Mohit Upadhyay and Anuj Kumar Upadhyay
Requires-Python: >=3.7
License-File: LICENSE
